classy_fire/__init__.py
classy_fire/base_classifier.py
classy_fire/llm_classifier.py
classy_fire/mcmc_classifier.py
classy_fire/__pycache__/__init__.cpython-39.pyc
classy_fire/__pycache__/classy_fire.cpython-39.pyc
classy_fire-0.2.1.dist-info/LICENSE
classy_fire-0.2.1.dist-info/METADATA
classy_fire-0.2.1.dist-info/WHEEL
classy_fire-0.2.1.dist-info/top_level.txt
classy_fire-0.2.1.dist-info/RECORD
