Metadata-Version: 2.1
Name: classy-fire
Version: 0.2.1
Summary: Classy-fire is multiclass text classification approach leveraging OpenAI LLM model APIs optimally using clever parameter tuning and prompting.
Author-email: Shay Ben-Elazar <shbenela@microsoft.com>
License: MIT License
Project-URL: Homepage, https://github.com/microsoft/classy-fire
Keywords: llm,classification,machine-learning
Classifier: License :: OSI Approved :: MIT License
Classifier: Programming Language :: Python
Classifier: Programming Language :: Python :: 3
Requires-Python: >=3.7
License-File: LICENSE
Provides-Extra: dev
Requires-Dist: pip-tools ; extra == 'dev'
Requires-Dist: pytest ; extra == 'dev'
Requires-Dist: tiktoken >=0.5.1 ; extra == 'dev'
Requires-Dist: openai ==1.2.4 ; extra == 'dev'
